{
    "alert_summary": {
        "category": [
            "malware-object"
        ], 
        "username": [], 
        "domain": "MGCAD", 
        "severity": "\u4e2d", 
        "runuser": [], 
        "hostname": "MGC20200235", 
        "ipaddr": "192.168.128.112", 
        "alert_id": "MGC1.MGC20200235_1625216702", 
        "alert_name": "", 
        "alert_time": "2021/07/02 18:03:24", 
        "action": [
            "ALERT"
        ]
    }, 
    "others": {
        "sender_name": "dgh"
    }, 
    "alert_src": {
        "product": "Fireeye HX", 
        "sensor_id": "86628149FD22", 
        "sensor_name": "hexktk724-hx-webui-1.hex01.helix.apps.fireeye.com", 
        "sensor_ipaddr": "", 
        "customer_name": "MGC1"
    }, 
    "alert_detail": {
        "status": "normal", 
        "event_detail": [
            {
                "category": "malware-object", 
                "ev_subtype": null, 
                "process_name": null, 
                "alert_id": "44244", 
                "process_id": null, 
                "alert_time": "2021/07/02 18:03:24", 
                "action": "ALERT", 
                "ev_type": "null", 
                "ev_target": ""
            }
        ], 
        "exploit_detail": [], 
        "ioc_detail": [], 
        "risk_score": 3, 
        "hostset": "Phase3_ALL_Prevent", 
        "process_detail": [], 
        "malware_detail": [
            {
                "name": "EICAR-Test-File (not a virus)", 
                "file_name": "C:\\Users\\csccc005\\AppData\\Local\\Microsoft\\Windows\\INetCache\\Low\\IE\\7OYF4E43\\eicar.com[1].txt", 
                "process_name": "C:\\Program Files (x86)\\Internet Explorer\\iexplore.exe", 
                "detection_category": "av", 
                "file_hash": "275a021bbfb6489e54d471899f7db9d1663fc695ec2fe2a2c4538aabf651fd0f", 
                "process_id": "16208", 
                "type": "malware", 
                "action": "clean", 
                "user_domain": "MGCAD", 
                "user_name": "CSCCC005", 
                "action_result": "fail"
            }
        ], 
        "os": "Windows 10 Pro", 
        "agent_id": "NI4X17djHT5duWiILg8T31"
    }, 
    "versions": "1.0"
}