{
	"id" : "00001-10-000044",
	"rev" : "0001",
	"enable" : "yes",
	"product" : "cbdefense",
	"type" : "condition",
	"reputation" : "white",
	"score" : 5,
	"value" : "itunes.exe",
	"detail" : {
		"data_position" : "process_info",
		"expected" : [
			{
				"field" : "command_line",
				"value" : "C:\\Program Files\\iTunes\\iTunes.exe",
				"type" : "exact"
			},
			{
				"field" : "parent_command_line",
				"value" : "C:\\Program Files\\iTunes\\iTunesHelper.exe",
				"type" : "exact"
			}
		],
		"exclusion" : []
	},
	"registered" : "2019/5/16",
	"user" : "ALL",
	"source" : "manual",
	"message" : "itunes normaly behavior."
}
