{
    "product": "carbonblack", 
    "global_access": [], 
    "alert_level": "4", 
    "important_tags": [], 
    "malicious_process": {
        "792-dfbea9e8c316d9bc118b454b0c722cd674c30d0a256340200e2c3a7480cba674-0": {
            "details": {
                "indicators": [
                    "POLICY_DENY", 
                    "RUN_BLACKLIST_APP"
                ], 
                "events": [
                    {
                        "runuser": "NT AUTHORITY\\SYSTEM", 
                        "ppid": "792-dfbea9e8c316d9bc118b454b0c722cd674c30d0a256340200e2c3a7480cba674-0", 
                        "description": "C:\\program files (x86)\\desktopcentral_agent\\bin\\dcagentservice.exe", 
                        "event_count": 1, 
                        "event_id": [
                            "e2c8e5011e7b11ecaafce9624e4b460b"
                        ], 
                        "event_summary": "c:\\program files (x86)\\desktopcentral_agent\\bin\\dcagentservice.exe:None[None]", 
                        "occurred": [
                            "2021/09/26 03:45:01"
                        ], 
                        "event_detail": {
                            "command_line": null, 
                            "hash": "093f54fe0056f264b100eb1b38533c283d8fa733bc4d284181dc8a6ad8a07c77", 
                            "reputation": "COMPANY_BLACK_LIST", 
                            "pid": null, 
                            "name": "c:\\program files (x86)\\desktopcentral_agent\\bin\\dcagentservice.exe"
                        }, 
                        "attack_phase": "INSTALL_RUN", 
                        "raw_ev_type": "childproc", 
                        "ev_type": "CREATE_PROCESS", 
                        "categories": [
                            "RUN_BLACKLIST_APP", 
                            "POLICY_DENY"
                        ]
                    }
                ], 
                "process_info": {
                    "parent_name": "wininit.exe", 
                    "parent_pid": 980, 
                    "command_line": "C:\\Windows\\system32\\services.exe", 
                    "pid": 792, 
                    "parent_path": "c:\\windows\\system32\\wininit.exe", 
                    "reputation": "TRUSTED_WHITE_LIST", 
                    "parent_reputation": "TRUSTED_WHITE_LIST", 
                    "parent_hash": "24a0e0ace66aeb97d101df232a571368c4068d9b46b9d3e9c22f8c10d0be7dc4", 
                    "path": "c:\\windows\\system32\\services.exe", 
                    "ppid": "792-dfbea9e8c316d9bc118b454b0c722cd674c30d0a256340200e2c3a7480cba674-0", 
                    "parent_command_line": null, 
                    "hash": "dfbea9e8c316d9bc118b454b0c722cd674c30d0a256340200e2c3a7480cba674"
                }
            }, 
            "message": "services.exe(792):[00001-10-001024:<temporary blackliste at desktopcentral_agent>]", 
            "flags": {
                "emerg": false, 
                "positive": false, 
                "cyfirma": false, 
                "main": true, 
                "gray": false
            }, 
            "app_name": "services.exe", 
            "shell_type": 0
        }
    }, 
    "cyfirma_detected_by_hash": [], 
    "nw_listen": false, 
    "base_severity": "\u4e2d", 
    "customer_name": "MYS1", 
    "shelltype_of_malprocess": 0, 
    "cyfirma_detected_by_nwdst": [], 
    "validator": "general_validator", 
    "is_except": false
}