{
    "product": "cbdefense", 
    "enable": "yes", 
    "score": 5, 
    "registered": "2020/3/18", 
    "rev": "0001", 
    "detail": {
        "expected": [
            {
                "field": "parent_name", 
                "type": "regexp", 
                "value": "(?i)svchost\\.exe"
            }, 
            {
                "field": "command_line", 
                "type": "regexp", 
                "value": "(?i)C:\\\\programdata\\\\lenovo-\\d+.vbs"
            }
        ], 
        "data_position": "process_info", 
        "exclusion": []
    }, 
    "value": "vb_script", 
    "source": "manual", 
    "reputation": "white", 
    "user": "all", 
    "message": "Lenovo PC Tool Script.", 
    "type": "condition", 
    "id": "00001-10-000231"
}